Metadata-Version: 1.1
Name: gzipi
Version: 0.1.1
Summary: Tools for indexing gzip files to support random-like access.
Home-page: https://github.com/ProfoundNetworks/gzipi
Author: Profound Networks
Author-email: mpenkov@profound.net
License: UNKNOWN
Download-URL: https://pypi.org/project/gzipi
Platform: UNKNOWN
Classifier: Intended Audience :: Developers
Classifier: Natural Language :: English
Classifier: Programming Language :: Python :: 3
Classifier: Programming Language :: Python :: 3.4
Classifier: Programming Language :: Python :: 3.5
Classifier: Programming Language :: Python :: 3.6
Classifier: Programming Language :: Python :: 3.7
Classifier: Programming Language :: Python :: 3.8
